Metadata-Version: 2.1
Name: random-quote-generator-by-eduuardoperez
Version: 0.1.0
Summary: 
Author: Eduardo Perez
Author-email: eduardo.perez@ripio.com
Requires-Python: >=3.11,<4.0
Classifier: Programming Language :: Python :: 3
Classifier: Programming Language :: Python :: 3.11
